maybankpdf2json/__init__.py
maybankpdf2json/extractor.py
maybankpdf2json/utils.py
maybankpdf2json-0.1.52.dist-info/METADATA
maybankpdf2json-0.1.52.dist-info/WHEEL
maybankpdf2json-0.1.52.dist-info/top_level.txt
maybankpdf2json-0.1.52.dist-info/RECORD
