Metadata-Version: 2.4
Name: maybankpdf2json
Version: 0.1.52
Summary: A package for extracting JSON data from Maybank PDF account statements
Home-page: https://github.com/nordinz7/maybankpdf2json
Author: Nordin
Author-email: Nordin <vipnordin@gmail.com>
Project-URL: Homepage, https://github.com/nordinz7/maybankpdf2json
Keywords: maybank,pdf,JSON,account statements,Email delivery statement,Malayan Banking
Classifier: Programming Language :: Python :: 3
Classifier: License :: OSI Approved :: MIT License
Classifier: Operating System :: OS Independent
Requires-Python: >=3.6
Requires-Dist: pdfplumber>=0.7.4
Requires-Dist: numpy>=1.24.3
Dynamic: author
Dynamic: home-page
Dynamic: requires-python
